spacy_readability/__init__.py
spacy_readability/words.py
spacy_readability-1.4.1.dist-info/LICENSE
spacy_readability-1.4.1.dist-info/WHEEL
spacy_readability-1.4.1.dist-info/METADATA
spacy_readability-1.4.1.dist-info/RECORD
